README.md
setup.py
XPRESSplot.egg-info/PKG-INFO
XPRESSplot.egg-info/SOURCES.txt
XPRESSplot.egg-info/dependency_links.txt
XPRESSplot.egg-info/not-zip-safe
XPRESSplot.egg-info/requires.txt
XPRESSplot.egg-info/top_level.txt
xpressplot/__init__.py
xpressplot/analyze.py
xpressplot/collapser.py
xpressplot/fetch.py
xpressplot/format.py
xpressplot/normalize.py
xpressplot/utils.py
xpressplot/utils_analyze.py