Metadata-Version: 2.1
Name: XPRESSplot
Version: 0.2.3
Summary: A toolkit for navigating and analyzing gene expression datasets
Home-page: https://github.com/XPRESSyourself/XPRESSplot
Author: Jordan Berg
Author-email: jordan.berg@biochem.utah.edu
License: GPL-3.0
Platform: UNKNOWN
Classifier: Development Status :: 5 - Production/Stable
Classifier: Intended Audience :: Science/Research
Classifier: Topic :: Scientific/Engineering :: Bio-Informatics
